sql_falp/conn.py
sql_falp-1.0.0.dist-info/METADATA
sql_falp-1.0.0.dist-info/WHEEL
sql_falp-1.0.0.dist-info/top_level.txt
sql_falp-1.0.0.dist-info/RECORD
