Metadata-Version: 2.1
Name: sql-falp
Version: 1.0.0
Summary: A package for falp sql databases connection
Author: mespinoza
Requires-Dist: pandas
Requires-Dist: sqlalchemy
Requires-Dist: unidecode
